snakenest/__init__.py
snakenest/configuration.py
snakenest/context.py
snakenest/event.py
snakenest/rulez.py
snakenest/singleton.py
snakenest-0.2.1.dist-info/METADATA
snakenest-0.2.1.dist-info/WHEEL
snakenest-0.2.1.dist-info/licenses/LICENSE.txt
snakenest-0.2.1.dist-info/RECORD
