Metadata-Version: 2.3
Name: SnakeNest
Version: 0.2.1
Summary: Snake Nest
Author-email: Roberto Di Rienzo <roberto.dirienzo@codelithic.com>
Maintainer-email: Roberto Di Rienzo <roberto.dirienzo@codelithic.com>
License-File: LICENSE.txt
Keywords: codelithic,injection,spring
Classifier: Development Status :: 4 - Beta
Classifier: Programming Language :: Python
Requires-Python: >=3.9
Requires-Dist: pyyaml
